{
  "typename": "User",
  "affiliatesHighlightedLabel": {},
  "businessAccount": {},
  "creatorSubscriptionsCount": 0,
  "hasGraduatedAccess": true,
  "highlightsInfo": {
    "canHighlightTweets": false,
    "highlightedTweets": "0"
  },
  "id": "VXNlcjoxNDA4NTQxMjk4",
  "isBlueVerified": false,
  "isProfileTranslatable": false,
  "legacy": {
    "canDm": true,
    "canMediaTag": true,
    "createdAt": "Mon May 06 19:40:09 +0000 2013",
    "defaultProfile": true,
    "defaultProfileImage": false,
    "description": "Technology journalist. AI Editor @TechCrunch (kyle.wiggers@techcrunch.com). Signal: kyle.901 Pronouns: he/him.",
    "entities": {
      "description": {
        "urls": []
      }
    },
    "fastFollowersCount": 0,
    "favouritesCount": 5737,
    "followersCount": 66792,
    "following": false,
    "friendsCount": 6066,
    "hasCustomTimelines": false,
    "isTranslator": false,
    "listedCount": 553,
    "location": "Manhattan, NY",
    "mediaCount": 386,
    "name": "Kyle Wiggers",
    "normalFollowersCount": 66792,
    "pinnedTweetIdsStr": [
      "1508519073960845312"
    ],
    "possiblySensitive": false,
    "profileBannerUrl": "https://pbs.twimg.com/profile_banners/1408541298/1721773919",
    "profileImageUrlHttps": "https://pbs.twimg.com/profile_images/1836973800082063360/X_1Y4dGj_normal.jpg",
    "profileInterstitialType": "",
    "screenName": "Kyle_L_Wiggers",
    "statusesCount": 16181,
    "translatorType": "none",
    "verified": false,
    "wantRetweets": false,
    "withheldInCountries": []
  },
  "legacyExtendedProfile": {},
  "premiumGiftingEligible": true,
  "profileImageShape": "Circle",
  "restId": "1408541298",
  "tipjarSettings": {},
  "userSeedTweetCount": 0,
  "verificationInfo": {
    "isIdentityVerified": false
  }
}