{
  "typename": "User",
  "affiliatesHighlightedLabel": {},
  "businessAccount": {},
  "creatorSubscriptionsCount": 0,
  "hasGraduatedAccess": true,
  "highlightsInfo": {
    "canHighlightTweets": false,
    "highlightedTweets": "0"
  },
  "id": "VXNlcjo4MjE3NjY2NjA4MjI2MjYzMDQ=",
  "isBlueVerified": false,
  "isProfileTranslatable": false,
  "legacy": {
    "canDm": true,
    "canMediaTag": false,
    "createdAt": "Wed Jan 18 17:10:14 +0000 2017",
    "defaultProfile": true,
    "defaultProfileImage": false,
    "description": "This account is no longer active. Please follow us on LinkedIn, Bluesky or subscribe to our newsletter to stay connected.",
    "entities": {
      "description": {
        "urls": []
      },
      "url": {
        "urls": [
          {
            "display_url": "partnershiponai.org/newsletter-sig…",
            "expanded_url": "https://partnershiponai.org/newsletter-signup/",
            "url": "https://t.co/cl5q31juTP",
            "indices": [
              0,
              23
            ]
          }
        ]
      }
    },
    "fastFollowersCount": 0,
    "favouritesCount": 2104,
    "followersCount": 30409,
    "following": false,
    "friendsCount": 765,
    "hasCustomTimelines": true,
    "isTranslator": false,
    "listedCount": 1265,
    "location": "",
    "mediaCount": 466,
    "name": "Partnership on AI",
    "normalFollowersCount": 30409,
    "pinnedTweetIdsStr": [],
    "possiblySensitive": false,
    "profileBannerUrl": "https://pbs.twimg.com/profile_banners/821766660822626304/1630443438",
    "profileImageUrlHttps": "https://pbs.twimg.com/profile_images/1432809740942327808/43YOM21u_normal.jpg",
    "profileInterstitialType": "",
    "screenName": "PartnershipAI",
    "statusesCount": 2580,
    "translatorType": "none",
    "url": "https://t.co/cl5q31juTP",
    "verified": false,
    "wantRetweets": false,
    "withheldInCountries": []
  },
  "legacyExtendedProfile": {},
  "premiumGiftingEligible": true,
  "profileImageShape": "Circle",
  "restId": "821766660822626304",
  "tipjarSettings": {},
  "userSeedTweetCount": 0,
  "verificationInfo": {
    "isIdentityVerified": false
  }
}